{
    "spring2017": {
        "KB": {
            "Name": "Kellen Barsley "
        },
        "JC": {
            "Name": "Jackson Cipriano"
        },
        "WD": {
            "Name": "Wyatt Damon"
        },
        "ME": {
            "Name": "Melanie Elenes"
        },
        "RE": {
            "Name": "Ricardo Estrada"
        },
        "EF": {
            "Name": "Evan Freer"
        },
        "IH": {
            "Name": "Isabella Herrick"
        },
        "AI": {
            "Name": "Andy Infante"
        },
        "DJ": {
            "Name": "Daniel Jilani"
        },
        "AL": {
            "Name": "Alan Lee"
        },
        "JM": {
            "Name": "Jose Marmolejo"
        },
        "NM": {
            "Name": "Nicolas Marselian"
        },
        "AN": {
            "Name": "Atharva Nanodkar"
        },
        "JR": {
            "Name": "Jayson Rosete"
        },
        "SC": {
            "Name": "Sophia Scipione"
        },
        "CT": {
            "Name": "Carlos Torres"
        }
    },

    "summer2017": {
        "SB": {
            "Name": "Sebastian Baehr"
        },
        "AMB": {
            "Name": "Andrea Marie Batoon"
        },
        "CD": {
            "Name": "Cooper D'Inca"
        },
        "WD": {
            "Name": "Wyatt Damon"
        },
        "DD": {
            "Name": "Dwight Diesmo"
        },
        "ME": {
            "Name": "Melanie Elenes"
        },
        "RE": {
            "Name": "Ricardo Estrada"
        },
        "LG": {
            "Name": "Lilah Guerra"
        },
        "KH": {
            "Name": "Kaitlyn Hannigan"
        },
        "IH": {
            "Name": "Isabella Herrick"
        },
        "DJ": {
            "Name": "Daniel Jilani"
        },
        "AL": {
            "Name": "Alan Lee"
        },
        "NM": {
            "Name": "Nicolas Marselian"
        },
        "AN": {
            "Name": "Asha Nahas"
        },
        "TN": {
            "Name": "Tori Nardoni"
        },
        "SS": {
            "Name": "Sophia Scipione"
        },
        "ST": {
            "Name": "Sophie Taylor"
        },
        "CZ": {
            "Name": "Caden Ziegler"
        }
    },
    
    "fall2017": {
        "SB": {
            "Name": "Sebastian Baehr"
        },
        "CD": {
            "Name": "Cooper D'Inca"
        },
        "DD": {
            "Name": "Dwight Diesmo"
        },
        "ME": {
            "Name": "Melanie Elenes"
        },
        "RE": {
            "Name": "Ricardo Estrada"
        },
        "LG": {
            "Name": "Lilah Guerra"
        },
        "IH": {
            "Name": "Isabella Herrick"
        },
        "DJ": {
            "Name": "Daniel Jilani"
        },
        "NM": {
            "Name": "Nicolas Marselian"
        },
        "TN": {
            "Name": "Tori Nardoni"
        },
        "SS": {
            "Name": "Sophia Scipione"
        },
        "ST": {
            "Name": "Sophie Taylor"
        },
        "CZ": {
            "Name": "Caden Ziegler"
        }
    },

    "winter2017": {
        "KA": {
            "Name": "Karina Arteaga"
        },
        "SB": {
            "Name": "Sebastian Baehr"
        },
        "CD": {
            "Name": "Cooper D'Inca"
        },
        "DD": {
            "Name": "Dwight Diesmo"
        },
        "ME": {
            "Name": "Melanie Elenes"
        },
        "RE": {
            "Name": "Ricardo Estrada"
        },
        "JG": {
            "Name": "Jaquelin Guzman"
        },
        "MH": {
            "Name": "Maddy Hood"
        },
        "DJ": {
            "Name": "Daniel Jilani"
        },
        "AM": {
            "Name": "Arianna Mangubat"
        },
        "NM": {
            "Name": "Nicolas Marselian"
        },
        "TN": {
            "Name": "Tori Nardoni"
        },
        "SS": {
            "Name": "Sophia Scipione"
        },
        "KS": {
            "Name": "Keaten Smith"
        },
        "NS": {
            "Name": "Nash Stephenson"
        },
        "CS": {
            "Name": "Cody Sylvester"
        },
        "JS": {
            "Name": "Jake Sylvester"
        },
        "ST": {
            "Name": "Sophie Taylor"
        },
        "CZ": {
            "Name": "Caden Ziegler"
        }
    },

    "spring2018": {
        "KA": {
            "Name": "Karina Arteaga"
        },
        "SB": {
            "Name": "Sebastian Baehr"
        },
        "AC": {
            "Name": "Alex Cano"
        },
        "CD": {
            "Name": "Cooper D'Inca"
        },
        "DD": {
            "Name": "Dwight Diesmo"
        },
        "ME": {
            "Name": "Melanie Elenes"
        },
        "RE": {
            "Name": "Ricardo Estrada"
        },
        "SG": {
            "Name": "Samantha Gronwald"
        },
        "JG": {
            "Name": "Jaquelin Guzman"
        },
        "MH": {
            "Name": "Maddy Hood"
        },
        "DJ": {
            "Name": "Daniel Jilani"
        },
        "TM": {
            "Name": "Tatum Maggiore"
        },
        "AM": {
            "Name": "Arianna Mangubat"
        },
        "NM": {
            "Name": "Nicolas Marselian"
        },
        "ZM": {
            "Name": "Zach Menes"
        },
        "TN": {
            "Name": "Tori Nardoni"
        },
        "SN": {
            "Name": "Sam Northrup"
        },
        "SO": {
            "Name": "Sam Ott"
        },
        "AP": {
            "Name": "Abby Pritchett"
        },
        "DDTR": {
            "Name": "Daniela Del Toro Ramirez"
        },
        "ZR": {
            "Name": "Zane Reis"
        },
        "TR": {
            "Name": "Tanner Rompal"
        },
        "NR": {
            "Name": "Noah Roth"
        },
        "CR": {
            "Name": "Cameron Rust"
        },
        "SS": {
            "Name": "Sophia Scipione"
        },
        "NS": {
            "Name": "Nicholas Slone"
        },
        "KS": {
            "Name": "Keaten Smith"
        },
        "NS": {
            "Name": "Nash Stephenson"
        },
        "CS": {
            "Name": "Cody Sylvester"
        },
        "JS": {
            "Name": "Jake Sylvester"
        },
        "ST": {
            "Name": "Sophie Taylor"
        },
        "MY": {
            "Name": "Mia Yates"
        },
        "CZ": {
            "Name": "Caden Ziegler"
        }
    } 
}
